{
  "name": "凌虛子（蒼狼）",
  "aliases": [
    "蒼狼"
  ],
  "description": "赴黑風山壽宴的道人，實為黑風怪同黨",
  "personality": [
    "陰險",
    "偽善",
    "貪利"
  ],
  "traits": [
    "狼形化人",
    "攜仙丹盤",
    "刻名留痕"
  ],
  "abilities": [
    "煉丹術",
    "幻化術",
    "潛行隱匿"
  ],
  "summary": "凌虛子在黑風山山坡遭孫悟空當場擊殺，其隨身仙丹盤上「凌虛子製」刻字暴露身份，成為悟空將計就計的關鍵線索。　凌虛子並未參與木仙庵詩會事件；當前檔案中所有新增事件均不涉及該角色，故無情節增量。",
  "events": [
    {
      "event_id": "ch017_010",
      "event_name": "誅狼得計",
      "event_status": "撞見悟空與菩薩，身份暴露",
      "character_decision": "試圖掩飾同黨身份",
      "decision_result": "被擊殺，丹盤落敵"
    }
  ]
}